fastquat/__init__.py
fastquat/quaternion.py
fastquat-0.5.2.dist-info/METADATA
fastquat-0.5.2.dist-info/WHEEL
fastquat-0.5.2.dist-info/RECORD
