Metadata-Version: 2.4
Name: FastQuat
Version: 0.5.2
Summary: High-performance quaternions with JAX support
Project-URL: homepage, https://fastquat.readthedocs.io
Project-URL: repository, https://github.com/CMBSciPol/fastquat
Author-email: Pierre Chanial <chanial@apc.in2p3.fr>
License-Expression: MIT
Classifier: Intended Audience :: Education
Classifier: Intended Audience :: Science/Research
Classifier: Programming Language :: Python :: 3.10
Classifier: Programming Language :: Python :: 3.11
Classifier: Programming Language :: Python :: 3.12
Classifier: Programming Language :: Python :: 3.13
Classifier: Topic :: Scientific/Engineering :: Astronomy
Classifier: Topic :: Scientific/Engineering :: Mathematics
Classifier: Topic :: Scientific/Engineering :: Physics
Requires-Python: >=3.10
Requires-Dist: jax>=0.4.0
Requires-Dist: jaxlib>=0.4.0
